gufunky/__init__.py
gufunky-1.0.6.dist-info/WHEEL
gufunky-1.0.6.dist-info/METADATA
gufunky-1.0.6.dist-info/RECORD
