Metadata-Version: 2.3
Name: gufunky
Version: 1.0.6
Summary: Looping through NumPy arrays like generalized universal functions.
Keywords: array,arrays,gufunc,gufuncs,numpy
Author: John Dawson
Author-email: John Dawson <john.a.dawson@proton.me>
License:                     GNU GENERAL PUBLIC LICENSE
Requires-Dist: numpy
Maintainer: John Dawson
Maintainer-email: John Dawson <john.a.dawson@proton.me>
Project-URL: Documentation, https://github.com/JohnADawson/gufunky/blob/master/src/gufunky/__init__.py
Project-URL: Homepage, https://github.com/JohnADawson/gufunky
